cg_auth/__init__.py
cg_auth/controllers/__init__.py
cg_auth/controllers/auth.py
cg_auth/controllers/auth_logs.py
cg_auth/controllers/auth_sessions.py
cg_auth/controllers/groups.py
cg_auth/controllers/user_codes.py
cg_auth/controllers/user_devices.py
cg_auth/controllers/users.py
cg_auth/handlers/__init__.py
cg_auth/handlers/auth_main.py
cg_auth/handlers/secure_handlers.py
cg_auth/handlers/security.py
cg_auth/models/__init__.py
cg_auth/models/constants.py
cg_auth/models/data_models.py
cg_auth-1.0.2.dist-info/METADATA
cg_auth-1.0.2.dist-info/RECORD
cg_auth-1.0.2.dist-info/WHEEL
cg_auth-1.0.2.dist-info/top_level.txt
