Metadata-Version: 2.1
Name: cg-auth
Version: 1.0.2
Summary: CodeGini Auth Library
Home-page: https://github.com/CodeGini/cg_auth
Author: Engr Munib
Author-email: munib@codegini.com
License: MIT
Platform: UNKNOWN
